{"distro":"bianbu","os_version":"Linux version 6.1.15 (root@bianbu-build-deb-37zn1-v692p) (gcc (Ubuntu 13.2.0-4ubuntu3-bb2) 13.2.0, GNU ld (GNU Binutils for Ubuntu) 2.41) #1.0 SMP PREEMPT Thu May 30 13:16:13 UTC 2024\n","kernel_version":"6.1.15\n","package_name":"nodejs","package_metadata":{"package_version":"18.13.0+dfsg1-1ubuntu2","package_pretty_name":"Node.js","package_type":"Javascript Runtime","package_description":"Evented I/O for V8 JavaScript - runtime executable"},"test_results":[{"test_name":"test.sh","output":"Package nodejs is installed.\nTemp dir: /tmp/tmp.cp23lxbeKL\nNode.js is functioning correctly.\nNode.js is functioning correctly.\n","passed":true}],"all_tests_passed":true}