{"distro":"fedora","os_version":"Linux version 6.12.7-200.0.riscv64.fc41.riscv64 (mockbuild@b085e57e93af4f97a92adef0cd6a5f7b) (gcc (GCC) 14.2.1 20240912 (Red Hat 14.2.1-3), GNU ld version 2.43.1-5.fc41) #1 SMP PREEMPT_DYNAMIC Sat Dec 28 10:55:11 EST 2024\n","kernel_version":"6.12.7-200.0.riscv64.fc41.riscv64\n","package_name":"nginx","package_metadata":{"package_version":"1.26.2","package_pretty_name":"Nginx","package_type":"Web Server","package_description":"high-performance web server and a reverse proxy server"},"test_results":[{"test_name":"test.sh","output":"Nothing to do.\nStarting nginx test...\nPackage nginx is not installed. Attempting to install...\nInstalling nginx...\nPackage           Arch    Version         Repository        Size\nInstalling:\n nginx            riscv64 2:1.26.2-1.fc41 fedora-riscv 119.1 KiB\nInstalling dependencies:\n gperftools-libs  riscv64 2.15-4.fc41     fedora-riscv   1.4 MiB\n nginx-core       riscv64 2:1.26.2-1.fc41 fedora-riscv   1.6 MiB\n nginx-filesystem noarch  2:1.26.2-1.fc41 fedora-riscv   0.0   B\n nginx-mimetypes  noarch  2.1.54-7.fc41   fedora-riscv  46.6 KiB\nInstalling weak dependencies:\n logrotate        riscv64 3.22.0-2.fc41   fedora-riscv 144.9 KiB\n\nTransaction Summary:\n Installing:         6 packages\n\nPackage nginx installed successfully.\nNginx version: 1.26.2\nChecking nginx configuration...\nCreating test index.html...\nValidating configuration syntax...\nNginx service is not running. Attempting to start...\nStarting nginx service...\nFailed to start Nginx service.\n","passed":false}],"all_tests_passed":false}